{
  "source_id": "nys_civil_service",
  "name": "NYS Civil Service",
  "url": "https://www.cs.ny.gov/examannouncements/types/oc/",
  "extracted_at": "2026-04-15T08:46:55Z",
  "links": [
    {
      "text": "Navigation menu",
      "href": "https://www.cs.ny.gov/examannouncements/types/oc/"
    },
    {
      "text": "Department of Civil Service",
      "href": "https://www.cs.ny.gov"
    },
    {
      "text": "Online Services",
      "href": "https://www.cs.ny.gov/examannouncements/types/oc/"
    },
    {
      "text": "Account Login",
      "href": "https://www.cs.ny.gov/home/myaccount/"
    },
    {
      "text": "Apply Online",
      "href": "https://www.cs.ny.gov/jobseeker/onlineapp/ocappinfo.cfm"
    },
    {
      "text": "My Examination Applications",
      "href": "https://www.cs.ny.gov/examannouncements/confirmation/history/index.cfm"
    },
    {
      "text": "Eligible Lists (ELMS Online)",
      "href": "https://www.cs.ny.gov/elmspublic/"
    },
    {
      "text": "Job Seekers",
      "href": "https://www.cs.ny.gov/examannouncements/types/oc/"
    },
    {
      "text": "Hiring for Emergency Limited Placement (HELP) program",
      "href": "https://www.cs.ny.gov/help/"
    },
    {
      "text": "Centers for Careers in Government (CCG)",
      "href": "https://www.cs.ny.gov/ccg/"
    },
    {
      "text": "State Examinations",
      "href": "https://www.cs.ny.gov/jobseeker/"
    },
    {
      "text": "Local Examinations",
      "href": "https://www.cs.ny.gov/jobseeker/local/"
    },
    {
      "text": "Veterans & Individuals With Disabilities",
      "href": "https://www.cs.ny.gov/rp55/"
    },
    {
      "text": "Student Internships",
      "href": "https://nysinternships.cs.ny.gov/nnyl/"
    },
    {
      "text": "StateJobsNY",
      "href": "https://statejobs.ny.gov/"
    },
    {
      "text": "New York State Fellowship Programs",
      "href": "https://www.ny.gov/programs/new-york-state-fellowship-programs"
    },
    {
      "text": "State Employees",
      "href": "https://www.cs.ny.gov/examannouncements/types/oc/"
    },
    {
      "text": "Health Benefits",
      "href": "https://www.cs.ny.gov/employee-benefits/login/index.cfm"
    },
    {
      "text": "Resources",
      "href": "https://www.cs.ny.gov/employees/state/"
    },
    {
      "text": "Paid Family Leave",
      "href": "https://www.cs.ny.gov/pfl/"
    },
    {
      "text": "Paid Parental Leave",
      "href": "https://www.cs.ny.gov/ppl/"
    },
    {
      "text": "Career Mobility Office",
      "href": "http://careermobilityoffice.cs.ny.gov/"
    },
    {
      "text": "Retirees",
      "href": "https://www.cs.ny.gov/examannouncements/types/oc/"
    },
    {
      "text": "Health Benefits",
      "href": "https://www.cs.ny.gov/employee-benefits/login/index-retiree.cfm"
    },
    {
      "text": "Resources",
      "href": "https://www.cs.ny.gov/retirees/resources.cfm/"
    },
    {
      "text": "Retirement Benefits",
      "href": "http://www.osc.state.ny.us/retire/"
    },
    {
      "text": "Working After Retirement",
      "href": "https://www.cs.ny.gov/retirees/workingafterretirement.cfm"
    },
    {
      "text": "HR Professionals",
      "href": "https://www.cs.ny.gov/examannouncements/types/oc/"
    },
    {
      "text": "State Government",
      "href": "https://www.cs.ny.gov/businesssuite/"
    },
    {
      "text": "Local Government",
      "href": "https://www.cs.ny.gov/hr/local_hrp.cfm"
    },
    {
      "text": "Civil Service Institute",
      "href": "https://www.cs.ny.gov/businesssuite/Training-and-Development/CSInstitute/"
    },
    {
      "text": "About Us",
      "href": "https://www.cs.ny.gov/examannouncements/types/oc/"
    },
    {
      "text": "About Us",
      "href": "https://www.cs.ny.gov/home/agency.overview.cfm"
    },
    {
      "text": "Frequently Asked Questions (FAQs)",
      "href": "https://www.cs.ny.gov/home/faq/"
    },
    {
      "text": "NY Hiring for Emergency Limited Placement Statewide",
      "href": "https://www.cs.ny.gov/help"
    },
    {
      "text": "Continuous Recruitment Examinations",
      "href": "https://www.cs.ny.gov/jobseeker/public/cr.cfm"
    },
    {
      "text": "Tentative Examination Schedule",
      "href": "https://www.cs.ny.gov/announ/tentative_schedule.cfm"
    },
    {
      "text": "Last Date to Apply",
      "href": "https://www.cs.ny.gov/examannouncements/types/oc/#ldf"
    },
    {
      "text": "Non−Refundable Processing Fee (Waivers available)",
      "href": "https://www.cs.ny.gov/examannouncements/types/oc/appinfo.cfm#Fee"
    },
    {
      "text": "Maintenance Supervisor 1 (Motor Equipment)",
      "href": "https://www.cs.ny.gov/examannouncements/announcements/oc/21-026020.cfm"
    },
    {
      "text": "Subscribe to this page",
      "href": "https://www.cs.ny.gov/examannouncements/rss/open-competitive.xml"
    },
    {
      "text": "What is this?",
      "href": "https://www.cs.ny.gov/home/feedhelp.cfm"
    },
    {
      "text": "Agency Overview",
      "href": "https://www.cs.ny.gov/home/agency.overview.cfm"
    },
    {
      "text": "Executive Leadership",
      "href": "https://www.cs.ny.gov/pio/admindirectory.cfm"
    },
    {
      "text": "Law, Rules & Regulations",
      "href": "https://www.cs.ny.gov/businesssuite/Civil-Service-Law/"
    },
    {
      "text": "Stay Informed",
      "href": "https://www.cs.ny.gov/pio/#4"
    },
    {
      "text": "Join #TeamCivilService",
      "href": "https://www.cs.ny.gov/careers/"
    },
    {
      "text": "Press Releases",
      "href": "https://www.cs.ny.gov/pio/pressreleases.cfm"
    },
    {
      "text": "Contact Civil Service",
      "href": "https://www.cs.ny.gov/home/contact.cfm"
    },
    {
      "text": "Equal Opportunity Policy",
      "href": "https://www.cs.ny.gov/home/eop.cfm"
    },
    {
      "text": "Language Access Information",
      "href": "https://www.cs.ny.gov/home/languageaccess.cfm"
    },
    {
      "text": "Reasonable Accommodation",
      "href": "https://www.cs.ny.gov/dpm/reasonaccom.cfm"
    },
    {
      "text": "Public Information",
      "href": "https://www.cs.ny.gov/pio/"
    },
    {
      "text": "Freedom of Information Law (FOIL)",
      "href": "https://www.cs.ny.gov/FOIL/"
    },
    {
      "text": "Open Meetings",
      "href": "https://www.cs.ny.gov/commission/Webcast/webcastlinks.cfm"
    },
    {
      "text": "Test Guides & Resource Booklets",
      "href": "https://www.cs.ny.gov/testing/testguides.cfm"
    },
    {
      "text": "Vendor Information",
      "href": "https://www.cs.ny.gov/pio/vendorinfo.cfm"
    },
    {
      "text": "DPM-100 Master Equal Employment Opportunity Data Collection Form",
      "href": "https://www.cs.ny.gov/examannouncements/ethnic/index.cfm"
    },
    {
      "text": "Executive Order 31",
      "href": "https://www.cs.ny.gov/eo31/index.cfm"
    },
    {
      "text": "Accessibility",
      "href": "https://www.cs.ny.gov/home/accessibility.cfm"
    },
    {
      "text": "Disclaimer",
      "href": "https://www.cs.ny.gov/home/disclaimer.cfm"
    },
    {
      "text": "Privacy Policy",
      "href": "https://www.cs.ny.gov/home/privacypolicy.cfm"
    },
    {
      "text": "FACEBOOK",
      "href": "https://www.facebook.com/nyscivilservice"
    },
    {
      "text": "INSTAGRAM",
      "href": "https://www.instagram.com/nyscivilservice/"
    },
    {
      "text": "LINKEDIN",
      "href": "https://www.linkedin.com/company/new-york-state-department-of-civil-service/"
    },
    {
      "text": "YOUTUBE",
      "href": "https://www.youtube.com/channel/UC-m6gXx7rL8hwBHmcbgWrXw"
    },
    {
      "text": "TWITTER",
      "href": "https://x.com/nyscivilservice"
    },
    {
      "text": "REGISTER NOW",
      "href": "https://www.ny.gov/services/register-vote"
    }
  ],
  "records": [
    {
      "exam_number": "21-026020",
      "title": "Maintenance Supervisor 1 (Motor Equipment)",
      "detail_url": "https://www.cs.ny.gov/examannouncements/announcements/oc/21-026020.cfm",
      "salary": "See Announcement",
      "deadline": "April 29, 2026",
      "fee": "$0",
      "salary_text": "See Announcement"
    }
  ],
  "record_count": 1,
  "record_fields_present": [
    "exam_number",
    "title",
    "detail_url",
    "salary",
    "deadline",
    "fee",
    "salary_text"
  ],
  "record_fingerprint": "0e1287a29e86098d",
  "summary_note": "",
  "exam_titles": [
    "Maintenance Supervisor 1 (Motor Equipment)"
  ],
  "dates": [
    "April 29, 2026"
  ],
  "keywords_found": [
    "exam",
    "announcement"
  ],
  "normalized_text": "21-026020 | Maintenance Supervisor 1 (Motor Equipment) | April 29, 2026 | See Announcement | $0 | https://www.cs.ny.gov/examannouncements/announcements/oc/21-026020.cfm"
}