{
  "source_id": "westchester_county",
  "name": "Westchester County Civil Service",
  "url": "http://exams.westchestergov.com/webexam/PE/listOpenToAllExams.htm",
  "extracted_at": "2026-04-25T08:06:53Z",
  "links": [
    {
      "text": "Skip to main content",
      "href": "https://exams.westchestergov.com/webexam/PE/listOpenToAllExams.htm#exam_content1"
    },
    {
      "text": "Scheduled Exams",
      "href": "https://exams.westchestergov.com/webexam/PE/scheduledExamsHome.htm"
    },
    {
      "text": "Continuous Recruitment Exams",
      "href": "https://exams.westchestergov.com/webexam/CR/crExamsHome.htm"
    },
    {
      "text": "Email Subscription",
      "href": "https://exams.westchestergov.com/webexam/emailSubscription/subscribe.htm"
    },
    {
      "text": "Login/Register",
      "href": "https://exams.westchestergov.com/webexam/login/login.htm"
    },
    {
      "text": "Home",
      "href": "https://exams.westchestergov.com/webexam/home/welcome.htm"
    },
    {
      "text": "View Cart",
      "href": "https://exams.westchestergov.com/webexam/cart/showCart.htm"
    },
    {
      "text": "Open to All",
      "href": "https://exams.westchestergov.com/webexam/PE/listOpenToAllExams.htm"
    },
    {
      "text": "County/WMC Promotional",
      "href": "https://exams.westchestergov.com/webexam/PE/listCountyWMCPromotionalExams.htm"
    },
    {
      "text": "Local Promotional",
      "href": "https://exams.westchestergov.com/webexam/PE/listLocalPromotionalExams.htm"
    },
    {
      "text": "Assistant Business Manager",
      "href": "http://www.westchestergov.com/hr/onlineexam/PE/OC/60062550.htm"
    },
    {
      "text": "Applying Online",
      "href": "https://humanresources.westchestercountyny.gov/applying-online"
    },
    {
      "text": "Using This Website",
      "href": "https://humanresources.westchestercountyny.gov/using-website"
    },
    {
      "text": "FAQ",
      "href": "https://humanresources.westchestercountyny.gov/faqs"
    },
    {
      "text": "Disclaimer/Privacy Policy",
      "href": "https://www.westchestercountyny.gov/disclaimer"
    },
    {
      "text": "Contact Us",
      "href": "https://humanresources.westchestercountyny.gov/contact-information"
    }
  ],
  "records": [
    {
      "exam_number": "60-062550",
      "agency": "School Districts",
      "title": "Assistant Business Manager",
      "detail_url": "http://www.westchestergov.com/hr/onlineexam/PE/OC/60062550.htm",
      "deadline": "05/06/2026",
      "exam_date": "06/13/2026",
      "salary": "Varies with School District",
      "fee": "$50.00",
      "salary_text": "Varies with School District"
    }
  ],
  "record_count": 1,
  "record_fields_present": [
    "exam_number",
    "agency",
    "title",
    "detail_url",
    "deadline",
    "exam_date",
    "salary",
    "fee",
    "salary_text"
  ],
  "record_fingerprint": "a9b68d0053e8dc4c",
  "summary_note": "",
  "exam_titles": [
    "Assistant Business Manager"
  ],
  "dates": [
    "05/06/2026",
    "06/13/2026"
  ],
  "keywords_found": [
    "exam"
  ],
  "normalized_text": "60-062550 | Assistant Business Manager | 05/06/2026 | 06/13/2026 | School Districts | Varies with School District | $50.00 | http://www.westchestergov.com/hr/onlineexam/PE/OC/60062550.htm"
}